pfsenseDHCP/__init__.py
pfsenseDHCP/pfsenseDHCP.py
pfsenseDHCP/deployment_files/DHCP_master_list.csv
pfsensedhcp-2.0.3.dist-info/licenses/LICENSE.txt
pfsensedhcp-2.0.3.dist-info/METADATA
pfsensedhcp-2.0.3.dist-info/WHEEL
pfsensedhcp-2.0.3.dist-info/entry_points.txt
pfsensedhcp-2.0.3.dist-info/top_level.txt
pfsensedhcp-2.0.3.dist-info/RECORD
