Metadata-Version: 2.4
Name: pfsenseDHCP
Version: 2.0.3
Summary: Merge DHCP static assignments .csv data into pfSense DHCP4 Server config file
Author-email: Chris Nelson <github@cjnaz.com>
License-Expression: MIT
Project-URL: repository, https://github.com/cjnaz/pfsenseDHCP
Keywords: cjnaz,pfsense,dhcp,kea,firewall
Classifier: Programming Language :: Python :: 3
Classifier: Topic :: System :: Networking
Classifier: Topic :: System :: Networking :: Firewalls
Requires-Python: >=3.9
License-File: LICENSE.txt
Requires-Dist: cjnfuncs>=3.1
Requires-Dist: lxml
Dynamic: license-file
